dls_marco_score_ispyb/VERSION
dls_marco_score_ispyb/__init__.py
dls_marco_score_ispyb/config.cfg
dls_marco_score_ispyb/score.py
dls_marco_score_ispyb/savedmodel/saved_model.pb
dls_marco_score_ispyb/savedmodel/variables/variables.data-00000-of-00001
dls_marco_score_ispyb/savedmodel/variables/variables.index
dls_marco_score_ispyb-1.0.1.dist-info/LICENSE
dls_marco_score_ispyb-1.0.1.dist-info/METADATA
dls_marco_score_ispyb-1.0.1.dist-info/WHEEL
dls_marco_score_ispyb-1.0.1.dist-info/top_level.txt
dls_marco_score_ispyb-1.0.1.dist-info/RECORD
