Metadata-Version: 2.1
Name: dls-marco-score-ispyb
Version: 1.0.1
Summary: UNKNOWN
Home-page: UNKNOWN
Author: 'Urszula Neuman',
Author-email: UNKNOWN
License: Apache License 2.0
Platform: UNKNOWN
Requires-Dist: mysql-connector-python (==8.0.18)
Requires-Dist: ispyb
Requires-Dist: tensorflow (==1.15.0)
